tinyjs/__init__.py
tinyjs/code_annotation.js
tinyjs/code_generator.py
tinyjs/grammer_rules.py
tinyjs/package.json
tinyjs-0.1.2.dist-info/licenses/LICENSE
tinyjs-0.1.2.dist-info/METADATA
tinyjs-0.1.2.dist-info/WHEEL
tinyjs-0.1.2.dist-info/top_level.txt
tinyjs-0.1.2.dist-info/RECORD
