Metadata-Version: 2.4
Name: tinyjs
Version: 0.1.2
Summary: A tiny JavaScript code generator
Author-email: almajd3713 <almajd3713@gmail.com>
License-Expression: MIT
Requires-Python: >=3.9
License-File: LICENSE
Requires-Dist: anytree==2.13.0
Requires-Dist: tqdm==4.67.1
Dynamic: license-file
